datamaestro_text/__init__.py
datamaestro_text/version.py
datamaestro_text/config/__init__.py
datamaestro_text/config/ai/quac.yaml
datamaestro_text/config/com/oscar-corpus.py
datamaestro_text/config/com/sentiment140.py
datamaestro_text/config/com/fastml/goodbooks-10k.yaml
datamaestro_text/config/com/github/ikat.py
datamaestro_text/config/com/github/aagohary/canard.py
datamaestro_text/config/com/github/apple/ml-qrecc.py
datamaestro_text/config/com/github/prdwb/orconvqa.py
datamaestro_text/config/com/github/soskek/bookcorpus.yaml
datamaestro_text/config/com/microsoft/wikiqa.yaml
datamaestro_text/config/com/microsoft/msmarco/passage.py
datamaestro_text/config/com/smashwords/bookcorpus.py
datamaestro_text/config/edu/cornell/nlvr.yaml
datamaestro_text/config/edu/stanford/__init__.py
datamaestro_text/config/edu/stanford/aclimdb.py
datamaestro_text/config/edu/stanford/glove.py
datamaestro_text/config/edu/stanford/im2p.yaml
datamaestro_text/config/edu/upenn/__init__.py
datamaestro_text/config/edu/upenn/ldc/__init__.py
datamaestro_text/config/edu/upenn/ldc/aquaint.py
datamaestro_text/config/fr/granddebat.py
datamaestro_text/config/gov/__init__.py
datamaestro_text/config/gov/nist/__init__.py
datamaestro_text/config/gov/nist/ir/covid.py
datamaestro_text/config/gov/nist/trec/__init__.py
datamaestro_text/config/gov/nist/trec/adhoc.py
datamaestro_text/config/gov/nist/trec/clueweb.yaml
datamaestro_text/config/gov/nist/trec/deeplearning.yaml
datamaestro_text/config/gov/nist/trec/index.yaml
datamaestro_text/config/gov/nist/trec/tipster.py
datamaestro_text/config/gov/nist/trec/web.yaml
datamaestro_text/config/io/github/rajpurkar/squad.yaml
datamaestro_text/config/io/github/thunlp/fewrel.py
datamaestro_text/config/io/metamind/research/__init__.py
datamaestro_text/config/io/metamind/research/wikitext.py
datamaestro_text/config/net/mattmahoney/enwiki.yaml
datamaestro_text/config/org/acm/recsys/cb2014.yaml
datamaestro_text/config/org/cocodataset/index.yaml
datamaestro_text-2026.1.1.dist-info/METADATA
datamaestro_text-2026.1.1.dist-info/WHEEL
datamaestro_text-2026.1.1.dist-info/entry_points.txt
datamaestro_text-2026.1.1.dist-info/licenses/LICENSE
datamaestro_text-2026.1.1.dist-info/RECORD
