Metadata-Version: 2.4
Name: datamaestro-text
Version: 2026.1.1
Summary: Datamaestro module for text-related datasets
Project-URL: Homepage, https://github.com/experimaestro/datamaestro_text
Project-URL: Documentation, https://datamaestro-text.readthedocs.io/en/latest/
Project-URL: Repository, https://github.com/experimaestro/datamaestro_text
Project-URL: Bug Tracker, https://github.com/experimaestro/datamaestro_text/issues
Author-email: Benjamin Piwowarski <benjamin@piwowarski.fr>
License: GPL-3.0-or-later
License-File: LICENSE
Keywords: dataset manager,experiments,information retrieval
Classifier: Development Status :: 4 - Beta
Classifier: Intended Audience :: Science/Research
Classifier: License :: OSI Approved :: GNU General Public License v3 (GPLv3)
Classifier: Operating System :: OS Independent
Classifier: Programming Language :: Python
Classifier: Programming Language :: Python :: 3
Classifier: Programming Language :: Python :: 3.10
Classifier: Programming Language :: Python :: 3.11
Classifier: Programming Language :: Python :: 3.12
Classifier: Topic :: Software Development :: Libraries :: Python Modules
Requires-Python: >=3.10
Requires-Dist: attrs
Requires-Dist: datamaestro>=1.6.2
Requires-Dist: experimaestro
Requires-Dist: ir-datasets>=0.5.8
Provides-Extra: dev
Requires-Dist: docutils; extra == 'dev'
Requires-Dist: flake8; extra == 'dev'
Requires-Dist: pytest; extra == 'dev'
Requires-Dist: sphinx<8; extra == 'dev'
Requires-Dist: sphobjinv; extra == 'dev'
